minerva_node/__init__.py
minerva_node/config.py
minerva_node/done_actions.py
minerva_node/error.py
minerva_node/log.py
minerva_node/node.py
minerva_node/node_harvest.py
minerva_node/pika_consumer.py
minerva_node/pluginapi.py
minerva_node/version.py
minerva_node/defaults/enqueue-node-job.conf
minerva_node/defaults/job-generator.conf
minerva_node-5.0.post0.dev6.dist-info/DESCRIPTION.rst
minerva_node-5.0.post0.dev6.dist-info/METADATA
minerva_node-5.0.post0.dev6.dist-info/RECORD
minerva_node-5.0.post0.dev6.dist-info/WHEEL
minerva_node-5.0.post0.dev6.dist-info/metadata.json
minerva_node-5.0.post0.dev6.dist-info/top_level.txt
minerva_node-5.0_0.dev6.data/scripts/minerva-node
