Metadata-Version: 2.0
Name: minerva-node
Version: 5.0-0.dev6
Summary: UNKNOWN
Home-page: UNKNOWN
Author: Hendrikx ITC
Author-email: info@hendrikx-itc.nl
License: UNKNOWN
Platform: UNKNOWN
Requires-Dist: minerva-etl (>=5.0.0.dev3)
Requires-Dist: pika (==0.13.0)
